odoo/addons/repair_reinvoice/README.rst
odoo/addons/repair_reinvoice/__init__.py
odoo/addons/repair_reinvoice/__manifest__.py
odoo/addons/repair_reinvoice/hooks.py
odoo/addons/repair_reinvoice/i18n/it.po
odoo/addons/repair_reinvoice/i18n/repair_reinvoice.pot
odoo/addons/repair_reinvoice/models/__init__.py
odoo/addons/repair_reinvoice/models/account_move_reversal.py
odoo/addons/repair_reinvoice/models/repair_order.py
odoo/addons/repair_reinvoice/readme/CONTRIBUTORS.rst
odoo/addons/repair_reinvoice/readme/DESCRIPTION.rst
odoo/addons/repair_reinvoice/readme/USAGE.rst
odoo/addons/repair_reinvoice/static/description/icon.png
odoo/addons/repair_reinvoice/static/description/index.html
odoo/addons/repair_reinvoice/tests/__init__.py
odoo/addons/repair_reinvoice/tests/test_repair_reinvoice.py
odoo/addons/repair_reinvoice/views/repair_views.xml
odoo_addon_repair_reinvoice-16.0.1.0.0.4.dist-info/METADATA
odoo_addon_repair_reinvoice-16.0.1.0.0.4.dist-info/WHEEL
odoo_addon_repair_reinvoice-16.0.1.0.0.4.dist-info/top_level.txt
odoo_addon_repair_reinvoice-16.0.1.0.0.4.dist-info/RECORD
